cmd/__init__.py
cmd/pip.py
parse/__init__.py
parse/config.py
parse/py_file.py
parse/yaml.py
fwheel-0.0.1.dev0.dist-info/LICENSE
fwheel-0.0.1.dev0.dist-info/METADATA
fwheel-0.0.1.dev0.dist-info/WHEEL
fwheel-0.0.1.dev0.dist-info/entry_points.txt
fwheel-0.0.1.dev0.dist-info/top_level.txt
fwheel-0.0.1.dev0.dist-info/RECORD
